x_config/__init__.py
x_config/__main__.py
x_config/errors.py
x_config/template.mako
x_config/x_secrets/__init__.py
x_config/x_secrets/aws.py
x_config/x_secrets/dotenv.py
x_config/x_secrets/kube.py
the_x_config-0.1.9.dist-info/METADATA
the_x_config-0.1.9.dist-info/WHEEL
the_x_config-0.1.9.dist-info/entry_points.txt
the_x_config-0.1.9.dist-info/RECORD
