Metadata-Version: 2.1
Name: the-x-config
Version: 0.1.9
Summary: Services configuration
License: MIT
Author: Dmytro Smyk
Author-email: porovozls@gmail.com
Requires-Python: >=3.9,<4
Classifier: License :: OSI Approved :: MIT License
Classifier: Programming Language :: Python :: 3
Classifier: Programming Language :: Python :: 3.9
Classifier: Programming Language :: Python :: 3.10
Classifier: Programming Language :: Python :: 3.11
Classifier: Programming Language :: Python :: 3.12
Requires-Dist: boto3 (>=1.19,<1.40)
Requires-Dist: kubernetes (>=32.0.1,<33.0.0)
Requires-Dist: mako (>=1.3,<1.4)
Requires-Dist: pydantic (>=2,<3)
Requires-Dist: python-dotenv (>=1,<2)
Requires-Dist: pyyaml (>=6,<7)
